<?xml version='1.0' encoding='utf-8'?>
<benchmark>
  <entries>
    <entry category="1_CelestialBody" id="1_CelestialBody_train_1">
      <text>109 Felicitas has a periapsis of 283326000000.</text>
      <triples>
        <triple>
          <sub>109_Felicitas</sub>
          <rel>periapsis</rel>
          <obj>283326000000</obj>
        </triple>
      </triples>
      <schemas>
        <schema>
          <sub>Asteroid</sub>
          <rel>periapsis</rel>
          <obj>number</obj>
        </schema>
      </schemas>
    </entry>
    <entry category="1_CelestialBody" id="1_CelestialBody_train_2">
      <text>The celestial body known as (66063) 1998 RO1 has a maximum temperature of 500 kelvins.</text>
      <triples>
        <triple>
          <sub>(66063)_1998_RO1</sub>
          <rel>maximumTemperature</rel>
          <obj>500</obj>
        </triple>
      </triples>
      <schemas>
        <schema>
          <sub>Asteroid</sub>
          <rel>maximumTemperature</rel>
          <obj>number</obj>
        </schema>
      </schemas>
    </entry>
    <entry category="1_CelestialBody" id="1_CelestialBody_train_3">
      <text>(410777) 2009 FD has a periapsis of 88234300000.</text>
      <triples>
        <triple>
          <sub>(410777)_2009_FD</sub>
          <rel>periapsis</rel>
          <obj>88234300000</obj>
        </triple>
      </triples>
      <schemas>
        <schema>
          <sub>Asteroid</sub>
          <rel>periapsis</rel>
          <obj>number</obj>
        </schema>
      </schemas>
    </entry>
    <entry category="1_CelestialBody" id="1_CelestialBody_train_4">
      <text>(15788) 1993 SB has an orbital period of 7729430000.</text>
      <triples>
        <triple>
          <sub>(15788)_1993_SB</sub>
          <rel>orbitalPeriod</rel>
          <obj>7729430000</obj>
        </triple>
      </triples>
      <schemas>
        <schema>
          <sub>Asteroid</sub>
          <rel>orbitalPeriod</rel>
          <obj>number</obj>
        </schema>
      </schemas>
    </entry>
    <entry category="1_CelestialBody" id="1_CelestialBody_train_5">
      <text>The rotation period for 1089 Tama is 17.28.</text>
      <triples>
        <triple>
          <sub>1089_Tama</sub>
          <rel>rotationPeriod</rel>
          <obj>17.28</obj>
        </triple>
      </triples>
      <schemas>
        <schema>
          <sub>Asteroid</sub>
          <rel>rotationPeriod</rel>
          <obj>number</obj>
        </schema>
      </schemas>
    </entry>
    <entry category="1_CelestialBody" id="1_CelestialBody_train_6">
      <text>The epoch date of 1089 Tama is 26 November 2005.</text>
      <triples>
        <triple>
          <sub>1089_Tama</sub>
          <rel>epoch</rel>
          <obj>2005-11-26</obj>
        </triple>
      </triples>
      <schemas>
        <schema>
          <sub>Asteroid</sub>
          <rel>epoch</rel>
          <obj>Date</obj>
        </schema>
      </schemas>
    </entry>
    <entry category="1_CelestialBody" id="1_CelestialBody_train_7">
      <text>(66063) 1998 RO1 has an orbital period of 360.29 days.</text>
      <triples>
        <triple>
          <sub>(66063)_1998_RO1</sub>
          <rel>orbitalPeriod</rel>
          <obj>360.29</obj>
        </triple>
      </triples>
      <schemas>
        <schema>
          <sub>Asteroid</sub>
          <rel>orbitalPeriod</rel>
          <obj>number</obj>
        </schema>
      </schemas>
    </entry>
    <entry category="1_CelestialBody" id="1_CelestialBody_train_8">
      <text>1928 SJ was the former name of 1101 Clematis.</text>
      <triples>
        <triple>
          <sub>1101_Clematis</sub>
          <rel>formerName</rel>
          <obj>1928_SJ</obj>
        </triple>
      </triples>
      <schemas>
        <schema>
          <sub>Asteroid</sub>
          <rel>formerName</rel>
          <obj>Asteroid</obj>
        </schema>
      </schemas>
    </entry>
    <entry category="1_CelestialBody" id="1_CelestialBody_train_9">
      <text>(19255) 1994 VK8 has a periapsis of 6155910000000.</text>
      <triples>
        <triple>
          <sub>(19255)_1994_VK8</sub>
          <rel>periapsis</rel>
          <obj>6155910000000</obj>
        </triple>
      </triples>
      <schemas>
        <schema>
          <sub>Asteroid</sub>
          <rel>periapsis</rel>
          <obj>number</obj>
        </schema>
      </schemas>
    </entry>
    <entry category="1_CelestialBody" id="1_CelestialBody_train_10">
      <text>109 Felicitas has a mass of 7.5 kilograms.</text>
      <triples>
        <triple>
          <sub>109_Felicitas</sub>
          <rel>mass</rel>
          <obj>7.5</obj>
        </triple>
      </triples>
      <schemas>
        <schema>
          <sub>Asteroid</sub>
          <rel>mass</rel>
          <obj>number</obj>
        </schema>
      </schemas>
    </entry>
    <entry category="1_CelestialBody" id="1_CelestialBody_train_11">
      <text>1089 Tama has a periapsis of 288749000000.</text>
      <triples>
        <triple>
          <sub>1089_Tama</sub>
          <rel>periapsis</rel>
          <obj>288749000000</obj>
        </triple>
      </triples>
      <schemas>
        <schema>
          <sub>Asteroid</sub>
          <rel>periapsis</rel>
          <obj>number</obj>
        </schema>
      </schemas>
    </entry>
    <entry category="1_CelestialBody" id="1_CelestialBody_train_12">
      <text>The maximum temperature of (410777) 2009 FD is 362 kelvins.</text>
      <triples>
        <triple>
          <sub>(410777)_2009_FD</sub>
          <rel>maximumTemperature</rel>
          <obj>362</obj>
        </triple>
      </triples>
      <schemas>
        <schema>
          <sub>Asteroid</sub>
          <rel>maximumTemperature</rel>
          <obj>number</obj>
        </schema>
      </schemas>
    </entry>
    <entry category="1_CelestialBody" id="1_CelestialBody_train_13">
      <text>The former name of 1099 Figneria is 1928 RQ.</text>
      <triples>
        <triple>
          <sub>1099_Figneria</sub>
          <rel>formerName</rel>
          <obj>1928_RQ</obj>
        </triple>
      </triples>
      <schemas>
        <schema>
          <sub>Asteroid</sub>
          <rel>formerName</rel>
          <obj>Asteroid</obj>
        </schema>
      </schemas>
    </entry>
    <entry category="1_CelestialBody" id="1_CelestialBody_train_14">
      <text>1001 Gaussia has an orbital period of 5.75 days.</text>
      <triples>
        <triple>
          <sub>1001_Gaussia</sub>
          <rel>orbitalPeriod</rel>
          <obj>5.75</obj>
        </triple>
      </triples>
      <schemas>
        <schema>
          <sub>Asteroid</sub>
          <rel>orbitalPeriod</rel>
          <obj>number</obj>
        </schema>
      </schemas>
    </entry>
    <entry category="1_CelestialBody" id="1_CelestialBody_train_15">
      <text>The celestial body known as 1001 Gaussia has a mean temperature of 154 kelvins.</text>
      <triples>
        <triple>
          <sub>1001_Gaussia</sub>
          <rel>meanTemperature</rel>
          <obj>154</obj>
        </triple>
      </triples>
      <schemas>
        <schema>
          <sub>Asteroid</sub>
          <rel>meanTemperature</rel>
          <obj>number</obj>
        </schema>
      </schemas>
    </entry>
    <entry category="1_CelestialBody" id="1_CelestialBody_train_16">
      <text>The periapsis of 1001 Gaussia is 419113394.55312 (kilometres).</text>
      <triples>
        <triple>
          <sub>1001_Gaussia</sub>
          <rel>periapsis</rel>
          <obj>419113394.55312</obj>
        </triple>
      </triples>
      <schemas>
        <schema>
          <sub>Asteroid</sub>
          <rel>periapsis</rel>
          <obj>number</obj>
        </schema>
      </schemas>
    </entry>
    <entry category="1_CelestialBody" id="1_CelestialBody_train_17">
      <text>The celestial body known as 110 Lydia was discovered by Alphonse Borrelly.</text>
      <triples>
        <triple>
          <sub>110_Lydia</sub>
          <rel>discoverer</rel>
          <obj>Alphonse_Borrelly</obj>
        </triple>
      </triples>
      <schemas>
        <schema>
          <sub>Asteroid</sub>
          <rel>discoverer</rel>
          <obj>Astronomer</obj>
        </schema>
      </schemas>
    </entry>
    <entry category="1_CelestialBody" id="1_CelestialBody_train_18">
      <text>101 Helena has a density of 2 grams per cubic centimetres.</text>
      <triples>
        <triple>
          <sub>101_Helena</sub>
          <rel>density</rel>
          <obj>2</obj>
        </triple>
      </triples>
      <schemas>
        <schema>
          <sub>Asteroid</sub>
          <rel>density</rel>
          <obj>number</obj>
        </schema>
      </schemas>
    </entry>
    <entry category="1_CelestialBody" id="1_CelestialBody_train_19">
      <text>James Craig Watson is a Canadian national.</text>
      <triples>
        <triple>
          <sub>James_Craig_Watson</sub>
          <rel>nationality</rel>
          <obj>Canada</obj>
        </triple>
      </triples>
      <schemas>
        <schema>
          <sub>Astronomer</sub>
          <rel>nationality</rel>
          <obj>Country</obj>
        </schema>
      </schemas>
    </entry>
    <entry category="1_CelestialBody" id="1_CelestialBody_train_20">
      <text>The epoch of (19255) 1994 VK8 is on 31 December 2006.</text>
      <triples>
        <triple>
          <sub>(19255)_1994_VK8</sub>
          <rel>epoch</rel>
          <obj>2006-12-31</obj>
        </triple>
      </triples>
      <schemas>
        <schema>
          <sub>Asteroid</sub>
          <rel>epoch</rel>
          <obj>Date</obj>
        </schema>
      </schemas>
    </entry>
    <entry category="1_CelestialBody" id="1_CelestialBody_train_21">
      <text>(29075) 1950 DA was discovered by Carl A. Wirtanen.</text>
      <triples>
        <triple>
          <sub>(29075)_1950_DA</sub>
          <rel>discoverer</rel>
          <obj>Carl_A._Wirtanen</obj>
        </triple>
      </triples>
      <schemas>
        <schema>
          <sub>Asteroid</sub>
          <rel>discoverer</rel>
          <obj>Astronomer</obj>
        </schema>
      </schemas>
    </entry>
    <entry category="1_CelestialBody" id="1_CelestialBody_train_22">
      <text>1089 Tama has a temperature of 179 kelvins.</text>
      <triples>
        <triple>
          <sub>1089_Tama</sub>
          <rel>temperature</rel>
          <obj>179</obj>
        </triple>
      </triples>
      <schemas>
        <schema>
          <sub>Asteroid</sub>
          <rel>temperature</rel>
          <obj>number</obj>
        </schema>
      </schemas>
    </entry>
    <entry category="1_CelestialBody" id="1_CelestialBody_train_23">
      <text>The discoverer of (15788) 1993 SB is Donal O'Ceallaigh.</text>
      <triples>
        <triple>
          <sub>(15788)_1993_SB</sub>
          <rel>discoverer</rel>
          <obj>Donal_O'Ceallaigh</obj>
        </triple>
      </triples>
      <schemas>
        <schema>
          <sub>Asteroid</sub>
          <rel>discoverer</rel>
          <obj>Astronomer</obj>
        </schema>
      </schemas>
    </entry>
    <entry category="1_CelestialBody" id="1_CelestialBody_train_24">
      <text>(29075) 1950 DA has a periapsis of 124950000000.</text>
      <triples>
        <triple>
          <sub>(29075)_1950_DA</sub>
          <rel>periapsis</rel>
          <obj>124950000000</obj>
        </triple>
      </triples>
      <schemas>
        <schema>
          <sub>Asteroid</sub>
          <rel>periapsis</rel>
          <obj>number</obj>
        </schema>
      </schemas>
    </entry>
    <entry category="1_CelestialBody" id="1_CelestialBody_train_25">
      <text>The orbital period of the asteroid 1147 Stavropolis is 1249.6 days.</text>
      <triples>
        <triple>
          <sub>1147_Stavropolis</sub>
          <rel>orbitalPeriod</rel>
          <obj>1249.6</obj>
        </triple>
      </triples>
      <schemas>
        <schema>
          <sub>Asteroid</sub>
          <rel>orbitalPeriod</rel>
          <obj>number</obj>
        </schema>
      </schemas>
    </entry>
    <entry category="1_CelestialBody" id="1_CelestialBody_train_26">
      <text>The periapsis of (15788) 1993 SB is 3997100000000.</text>
      <triples>
        <triple>
          <sub>(15788)_1993_SB</sub>
          <rel>periapsis</rel>
          <obj>3997100000000</obj>
        </triple>
      </triples>
      <schemas>
        <schema>
          <sub>Asteroid</sub>
          <rel>periapsis</rel>
          <obj>number</obj>
        </schema>
      </schemas>
    </entry>
    <entry category="1_CelestialBody" id="1_CelestialBody_train_27">
      <text>The epoch date of (410777) 2009 FD is 27 June 2015.</text>
      <triples>
        <triple>
          <sub>(410777)_2009_FD</sub>
          <rel>epoch</rel>
          <obj>2015-06-27</obj>
        </triple>
      </triples>
      <schemas>
        <schema>
          <sub>Asteroid</sub>
          <rel>epoch</rel>
          <obj>Date</obj>
        </schema>
      </schemas>
    </entry>
    <entry category="1_CelestialBody" id="1_CelestialBody_train_28">
      <text>110 Lydia has a temperature of 168 kelvins.</text>
      <triples>
        <triple>
          <sub>110_Lydia</sub>
          <rel>temperature</rel>
          <obj>168</obj>
        </triple>
      </triples>
      <schemas>
        <schema>
          <sub>Asteroid</sub>
          <rel>temperature</rel>
          <obj>number</obj>
        </schema>
      </schemas>
    </entry>
    <entry category="1_CelestialBody" id="1_CelestialBody_train_29">
      <text>103 Hera has an orbital period of 1622.213 days.</text>
      <triples>
        <triple>
          <sub>103_Hera</sub>
          <rel>orbitalPeriod</rel>
          <obj>1622.213</obj>
        </triple>
      </triples>
      <schemas>
        <schema>
          <sub>Asteroid</sub>
          <rel>orbitalPeriod</rel>
          <obj>number</obj>
        </schema>
      </schemas>
    </entry>
    <entry category="1_CelestialBody" id="1_CelestialBody_train_30">
      <text>Iwan P. Williams discovered (15788) 1993 SB.</text>
      <triples>
        <triple>
          <sub>(15788)_1993_SB</sub>
          <rel>discoverer</rel>
          <obj>Iwan_P._Williams</obj>
        </triple>
      </triples>
      <schemas>
        <schema>
          <sub>Asteroid</sub>
          <rel>discoverer</rel>
          <obj>Astronomer</obj>
        </schema>
      </schemas>
    </entry>
    <entry category="1_CelestialBody" id="1_CelestialBody_train_31">
      <text>101 Helena has an average speed of 18.44 km per secs.</text>
      <triples>
        <triple>
          <sub>101_Helena</sub>
          <rel>averageSpeed</rel>
          <obj>18.44</obj>
        </triple>
      </triples>
      <schemas>
        <schema>
          <sub>Asteroid</sub>
          <rel>averageSpeed</rel>
          <obj>number</obj>
        </schema>
      </schemas>
    </entry>
    <entry category="1_CelestialBody" id="1_CelestialBody_train_32">
      <text>11264 Claudiomaccone was discovered by Nikolai Chernykh.</text>
      <triples>
        <triple>
          <sub>11264_Claudiomaccone</sub>
          <rel>discoverer</rel>
          <obj>Nikolai_Chernykh</obj>
        </triple>
      </triples>
      <schemas>
        <schema>
          <sub>Asteroid</sub>
          <rel>discoverer</rel>
          <obj>Astronomer</obj>
        </schema>
      </schemas>
    </entry>
    <entry category="1_CelestialBody" id="1_CelestialBody_train_33">
      <text>(66063) 1998 RO1 has an escape velocity of 0.0999 kilometres per second.</text>
      <triples>
        <triple>
          <sub>(66063)_1998_RO1</sub>
          <rel>escapeVelocity</rel>
          <obj>0.0999</obj>
        </triple>
      </triples>
      <schemas>
        <schema>
          <sub>Asteroid</sub>
          <rel>escapeVelocity</rel>
          <obj>number</obj>
        </schema>
      </schemas>
    </entry>
    <entry category="1_CelestialBody" id="1_CelestialBody_train_34">
      <text>James Craig Watson has his origins in Canada.</text>
      <triples>
        <triple>
          <sub>James_Craig_Watson</sub>
          <rel>stateOfOrigin</rel>
          <obj>Canada</obj>
        </triple>
      </triples>
      <schemas>
        <schema>
          <sub>Astronomer</sub>
          <rel>stateOfOrigin</rel>
          <obj>Country</obj>
        </schema>
      </schemas>
    </entry>
    <entry category="1_CelestialBody" id="1_CelestialBody_train_35">
      <text>110 Lydia has an apoapsis of 440756000 kilometres.</text>
      <triples>
        <triple>
          <sub>110_Lydia</sub>
          <rel>apoapsis</rel>
          <obj>440756000</obj>
        </triple>
      </triples>
      <schemas>
        <schema>
          <sub>Asteroid</sub>
          <rel>apoapsis</rel>
          <obj>number</obj>
        </schema>
      </schemas>
    </entry>
    <entry category="1_CelestialBody" id="1_CelestialBody_train_36">
      <text>101 Helena has a mass of 3 kgs.</text>
      <triples>
        <triple>
          <sub>101_Helena</sub>
          <rel>mass</rel>
          <obj>3</obj>
        </triple>
      </triples>
      <schemas>
        <schema>
          <sub>Asteroid</sub>
          <rel>mass</rel>
          <obj>number</obj>
        </schema>
      </schemas>
    </entry>
    <entry category="1_CelestialBody" id="1_CelestialBody_train_37">
      <text>10 Hygiea has a temperature of 164 kelvins.</text>
      <triples>
        <triple>
          <sub>10_Hygiea</sub>
          <rel>temperature</rel>
          <obj>164</obj>
        </triple>
      </triples>
      <schemas>
        <schema>
          <sub>Asteroid</sub>
          <rel>temperature</rel>
          <obj>number</obj>
        </schema>
      </schemas>
    </entry>
    <entry category="1_CelestialBody" id="1_CelestialBody_train_38">
      <text>103 Hera has the escape velocity of 0.0482 km per sec.</text>
      <triples>
        <triple>
          <sub>103_Hera</sub>
          <rel>escapeVelocity</rel>
          <obj>0.0482</obj>
        </triple>
      </triples>
      <schemas>
        <schema>
          <sub>Asteroid</sub>
          <rel>escapeVelocity</rel>
          <obj>number</obj>
        </schema>
      </schemas>
    </entry>
    <entry category="1_CelestialBody" id="1_CelestialBody_train_39">
      <text>101 Helena was discovered by James Craig Watson.</text>
      <triples>
        <triple>
          <sub>101_Helena</sub>
          <rel>discoverer</rel>
          <obj>James_Craig_Watson</obj>
        </triple>
      </triples>
      <schemas>
        <schema>
          <sub>Asteroid</sub>
          <rel>discoverer</rel>
          <obj>Astronomer</obj>
        </schema>
      </schemas>
    </entry>
    <entry category="1_CelestialBody" id="1_CelestialBody_train_40">
      <text>The epoch date for 1099 Figneria is 31 December 2006.</text>
      <triples>
        <triple>
          <sub>1099_Figneria</sub>
          <rel>epoch</rel>
          <obj>2006-12-31</obj>
        </triple>
      </triples>
      <schemas>
        <schema>
          <sub>Asteroid</sub>
          <rel>epoch</rel>
          <obj>Date</obj>
        </schema>
      </schemas>
    </entry>
    <entry category="1_CelestialBody" id="1_CelestialBody_train_41">
      <text>The celestial body known as 103 Hera has a temperature of 170 kelvins.</text>
      <triples>
        <triple>
          <sub>103_Hera</sub>
          <rel>temperature</rel>
          <obj>170</obj>
        </triple>
      </triples>
      <schemas>
        <schema>
          <sub>Asteroid</sub>
          <rel>temperature</rel>
          <obj>number</obj>
        </schema>
      </schemas>
    </entry>
    <entry category="1_CelestialBody" id="1_CelestialBody_train_42">
      <text>1001 Gaussia has an absolute magnitude of 9.7.</text>
      <triples>
        <triple>
          <sub>1001_Gaussia</sub>
          <rel>absoluteMagnitude</rel>
          <obj>9.7</obj>
        </triple>
      </triples>
      <schemas>
        <schema>
          <sub>Asteroid</sub>
          <rel>absoluteMagnitude</rel>
          <obj>number</obj>
        </schema>
      </schemas>
    </entry>
    <entry category="1_CelestialBody" id="1_CelestialBody_train_43">
      <text>1101 Clematis has an epoch date of December 31st 2006.</text>
      <triples>
        <triple>
          <sub>1101_Clematis</sub>
          <rel>epoch</rel>
          <obj>2006-12-31</obj>
        </triple>
      </triples>
      <schemas>
        <schema>
          <sub>Asteroid</sub>
          <rel>epoch</rel>
          <obj>Date</obj>
        </schema>
      </schemas>
    </entry>
    <entry category="1_CelestialBody" id="1_CelestialBody_train_44">
      <text>1097 Vicia has an orbital period of 135589000.</text>
      <triples>
        <triple>
          <sub>1097_Vicia</sub>
          <rel>orbitalPeriod</rel>
          <obj>135589000</obj>
        </triple>
      </triples>
      <schemas>
        <schema>
          <sub>Asteroid</sub>
          <rel>orbitalPeriod</rel>
          <obj>number</obj>
        </schema>
      </schemas>
    </entry>
    <entry category="1_CelestialBody" id="1_CelestialBody_train_45">
      <text>(66063) 1998 RO1 has a mean temperature of 265 kelvins.</text>
      <triples>
        <triple>
          <sub>(66063)_1998_RO1</sub>
          <rel>meanTemperature</rel>
          <obj>265</obj>
        </triple>
      </triples>
      <schemas>
        <schema>
          <sub>Asteroid</sub>
          <rel>meanTemperature</rel>
          <obj>number</obj>
        </schema>
      </schemas>
    </entry>
    <entry category="1_CelestialBody" id="1_CelestialBody_train_46">
      <text>1001 Gaussia has a rotation period of 33012.</text>
      <triples>
        <triple>
          <sub>1001_Gaussia</sub>
          <rel>rotationPeriod</rel>
          <obj>33012</obj>
        </triple>
      </triples>
      <schemas>
        <schema>
          <sub>Asteroid</sub>
          <rel>rotationPeriod</rel>
          <obj>number</obj>
        </schema>
      </schemas>
    </entry>
    <entry category="1_CelestialBody" id="1_CelestialBody_train_47">
      <text>(15788) 1993 SB has an epoch date of March 6th 2006.</text>
      <triples>
        <triple>
          <sub>(15788)_1993_SB</sub>
          <rel>epoch</rel>
          <obj>2006-03-06</obj>
        </triple>
      </triples>
      <schemas>
        <schema>
          <sub>Asteroid</sub>
          <rel>epoch</rel>
          <obj>Date</obj>
        </schema>
      </schemas>
    </entry>
    <entry category="1_CelestialBody" id="1_CelestialBody_train_48">
      <text>The asteroid 1147 Stavropolis was discovered on the 11th of June 1929.</text>
      <triples>
        <triple>
          <sub>1147_Stavropolis</sub>
          <rel>discovered</rel>
          <obj>1929-06-11</obj>
        </triple>
      </triples>
      <schemas>
        <schema>
          <sub>Asteroid</sub>
          <rel>discovered</rel>
          <obj>Date</obj>
        </schema>
      </schemas>
    </entry>
    <entry category="1_CelestialBody" id="1_CelestialBody_train_49">
      <text>The celestial body known as 109 Felicitas has a rotation period of 47487.6.</text>
      <triples>
        <triple>
          <sub>109_Felicitas</sub>
          <rel>rotationPeriod</rel>
          <obj>47487.6</obj>
        </triple>
      </triples>
      <schemas>
        <schema>
          <sub>Asteroid</sub>
          <rel>rotationPeriod</rel>
          <obj>number</obj>
        </schema>
      </schemas>
    </entry>
    <entry category="1_CelestialBody" id="1_CelestialBody_train_50">
      <text>1000 Piazzia has the mass of 1.1 kilograms.</text>
      <triples>
        <triple>
          <sub>1000_Piazzia</sub>
          <rel>mass</rel>
          <obj>1.1</obj>
        </triple>
      </triples>
      <schemas>
        <schema>
          <sub>Asteroid</sub>
          <rel>mass</rel>
          <obj>number</obj>
        </schema>
      </schemas>
    </entry>
    <entry category="1_CelestialBody" id="1_CelestialBody_train_51">
      <text>(66063) 1998 RO1 has an epoch date of 4 November 2013.</text>
      <triples>
        <triple>
          <sub>(66063)_1998_RO1</sub>
          <rel>epoch</rel>
          <obj>2013-11-04</obj>
        </triple>
      </triples>
      <schemas>
        <schema>
          <sub>Asteroid</sub>
          <rel>epoch</rel>
          <obj>Date</obj>
        </schema>
      </schemas>
    </entry>
    <entry category="1_CelestialBody" id="1_CelestialBody_train_52">
      <text>1097 Vicia has an escape velocity of 0.0112 kilometres per second.</text>
      <triples>
        <triple>
          <sub>1097_Vicia</sub>
          <rel>escapeVelocity</rel>
          <obj>0.0112</obj>
        </triple>
      </triples>
      <schemas>
        <schema>
          <sub>Asteroid</sub>
          <rel>escapeVelocity</rel>
          <obj>number</obj>
        </schema>
      </schemas>
    </entry>
    <entry category="1_CelestialBody" id="1_CelestialBody_train_53">
      <text>103 Hera has an average speed of 18.09 kilometres per second.</text>
      <triples>
        <triple>
          <sub>103_Hera</sub>
          <rel>averageSpeed</rel>
          <obj>18.09</obj>
        </triple>
      </triples>
      <schemas>
        <schema>
          <sub>Asteroid</sub>
          <rel>averageSpeed</rel>
          <obj>number</obj>
        </schema>
      </schemas>
    </entry>
    <entry category="1_CelestialBody" id="1_CelestialBody_train_54">
      <text>The rotation period for 11264 Claudiomaccone is 11473.9.</text>
      <triples>
        <triple>
          <sub>11264_Claudiomaccone</sub>
          <rel>rotationPeriod</rel>
          <obj>11473.9</obj>
        </triple>
      </triples>
      <schemas>
        <schema>
          <sub>Asteroid</sub>
          <rel>rotationPeriod</rel>
          <obj>number</obj>
        </schema>
      </schemas>
    </entry>
    <entry category="1_CelestialBody" id="1_CelestialBody_train_55">
      <text>10 Hygiea has an orbital period of 5.57 days.</text>
      <triples>
        <triple>
          <sub>10_Hygiea</sub>
          <rel>orbitalPeriod</rel>
          <obj>5.57</obj>
        </triple>
      </triples>
      <schemas>
        <schema>
          <sub>Asteroid</sub>
          <rel>orbitalPeriod</rel>
          <obj>number</obj>
        </schema>
      </schemas>
    </entry>
    <entry category="1_CelestialBody" id="1_CelestialBody_train_56">
      <text>N. R. Pogson died in Chennai.</text>
      <triples>
        <triple>
          <sub>N._R._Pogson</sub>
          <rel>deathPlace</rel>
          <obj>Chennai</obj>
        </triple>
      </triples>
      <schemas>
        <schema>
          <sub>Astronomer</sub>
          <rel>deathPlace</rel>
          <obj>City</obj>
        </schema>
      </schemas>
    </entry>
    <entry category="1_CelestialBody" id="1_CelestialBody_train_57">
      <text>109 Felicitas has an escape velocity of 0.0473 kilometres per second.</text>
      <triples>
        <triple>
          <sub>109_Felicitas</sub>
          <rel>escapeVelocity</rel>
          <obj>0.0473</obj>
        </triple>
      </triples>
      <schemas>
        <schema>
          <sub>Asteroid</sub>
          <rel>escapeVelocity</rel>
          <obj>number</obj>
        </schema>
      </schemas>
    </entry>
    <entry category="1_CelestialBody" id="1_CelestialBody_train_58">
      <text>109 Felicitas has a temperature of 170 kelvins.</text>
      <triples>
        <triple>
          <sub>109_Felicitas</sub>
          <rel>temperature</rel>
          <obj>170</obj>
        </triple>
      </triples>
      <schemas>
        <schema>
          <sub>Asteroid</sub>
          <rel>temperature</rel>
          <obj>number</obj>
        </schema>
      </schemas>
    </entry>
    <entry category="1_CelestialBody" id="1_CelestialBody_train_59">
      <text>James Craig Watson died of peritonitis.</text>
      <triples>
        <triple>
          <sub>James_Craig_Watson</sub>
          <rel>deathCause</rel>
          <obj>Peritonitis</obj>
        </triple>
      </triples>
      <schemas>
        <schema>
          <sub>Astronomer</sub>
          <rel>deathCause</rel>
          <obj>Disease</obj>
        </schema>
      </schemas>
    </entry>
    <entry category="1_CelestialBody" id="1_CelestialBody_train_60">
      <text>1101 Clematis has a temperature of 155 kelvins.</text>
      <triples>
        <triple>
          <sub>1101_Clematis</sub>
          <rel>temperature</rel>
          <obj>155</obj>
        </triple>
      </triples>
      <schemas>
        <schema>
          <sub>Asteroid</sub>
          <rel>temperature</rel>
          <obj>number</obj>
        </schema>
      </schemas>
    </entry>
    <entry category="1_CelestialBody" id="1_CelestialBody_train_61">
      <text>The periapsis of 1000 Piazzia is 352497000000.</text>
      <triples>
        <triple>
          <sub>1000_Piazzia</sub>
          <rel>periapsis</rel>
          <obj>352497000000</obj>
        </triple>
      </triples>
      <schemas>
        <schema>
          <sub>Asteroid</sub>
          <rel>periapsis</rel>
          <obj>number</obj>
        </schema>
      </schemas>
    </entry>
    <entry category="1_CelestialBody" id="1_CelestialBody_train_62">
      <text>110 Lydia has a periapsis measurement of 377016000000.</text>
      <triples>
        <triple>
          <sub>110_Lydia</sub>
          <rel>periapsis</rel>
          <obj>377016000000</obj>
        </triple>
      </triples>
      <schemas>
        <schema>
          <sub>Asteroid</sub>
          <rel>periapsis</rel>
          <obj>number</obj>
        </schema>
      </schemas>
    </entry>
    <entry category="1_CelestialBody" id="1_CelestialBody_train_63">
      <text>110 Lydia has a mass of 6.7 kilograms.</text>
      <triples>
        <triple>
          <sub>110_Lydia</sub>
          <rel>mass</rel>
          <obj>6.7</obj>
        </triple>
      </triples>
      <schemas>
        <schema>
          <sub>Asteroid</sub>
          <rel>mass</rel>
          <obj>number</obj>
        </schema>
      </schemas>
    </entry>
    <entry category="1_CelestialBody" id="1_CelestialBody_train_64">
      <text>1099 Figneria has an apoapsis of 605718000 kilometres.</text>
      <triples>
        <triple>
          <sub>1099_Figneria</sub>
          <rel>apoapsis</rel>
          <obj>605718000</obj>
        </triple>
      </triples>
      <schemas>
        <schema>
          <sub>Asteroid</sub>
          <rel>apoapsis</rel>
          <obj>number</obj>
        </schema>
      </schemas>
    </entry>
    <entry category="1_CelestialBody" id="1_CelestialBody_train_65">
      <text>1101 Clematis has the average speed of 16.54 km/s.</text>
      <triples>
        <triple>
          <sub>1101_Clematis</sub>
          <rel>averageSpeed</rel>
          <obj>16.54</obj>
        </triple>
      </triples>
      <schemas>
        <schema>
          <sub>Asteroid</sub>
          <rel>averageSpeed</rel>
          <obj>number</obj>
        </schema>
      </schemas>
    </entry>
    <entry category="1_CelestialBody" id="1_CelestialBody_train_66">
      <text>The periapsis measurement of 10 Hygiea is 416136000000.</text>
      <triples>
        <triple>
          <sub>10_Hygiea</sub>
          <rel>periapsis</rel>
          <obj>416136000000</obj>
        </triple>
      </triples>
      <schemas>
        <schema>
          <sub>Asteroid</sub>
          <rel>periapsis</rel>
          <obj>number</obj>
        </schema>
      </schemas>
    </entry>
    <entry category="1_CelestialBody" id="1_CelestialBody_train_67">
      <text>The apoapsis of 1147 Stavropolis is 418476000000.</text>
      <triples>
        <triple>
          <sub>1147_Stavropolis</sub>
          <rel>apoapsis</rel>
          <obj>418476000000</obj>
        </triple>
      </triples>
      <schemas>
        <schema>
          <sub>Asteroid</sub>
          <rel>apoapsis</rel>
          <obj>number</obj>
        </schema>
      </schemas>
    </entry>
    <entry category="1_CelestialBody" id="1_CelestialBody_train_68">
      <text>101 Helena has a periapsis of 331683000 kilometres.</text>
      <triples>
        <triple>
          <sub>101_Helena</sub>
          <rel>periapsis</rel>
          <obj>331683000</obj>
        </triple>
      </triples>
      <schemas>
        <schema>
          <sub>Asteroid</sub>
          <rel>periapsis</rel>
          <obj>number</obj>
        </schema>
      </schemas>
    </entry>
    <entry category="1_CelestialBody" id="1_CelestialBody_train_69">
      <text>(19255) 1994 VK8 has an apoapsis of 6603633000 kilometres.</text>
      <triples>
        <triple>
          <sub>(19255)_1994_VK8</sub>
          <rel>apoapsis</rel>
          <obj>6603633000</obj>
        </triple>
      </triples>
      <schemas>
        <schema>
          <sub>Asteroid</sub>
          <rel>apoapsis</rel>
          <obj>number</obj>
        </schema>
      </schemas>
    </entry>
    <entry category="1_CelestialBody" id="1_CelestialBody_train_70">
      <text>(29075) 1950 DA has a mass of 4 kilograms.</text>
      <triples>
        <triple>
          <sub>(29075)_1950_DA</sub>
          <rel>mass</rel>
          <obj>4</obj>
        </triple>
      </triples>
      <schemas>
        <schema>
          <sub>Asteroid</sub>
          <rel>mass</rel>
          <obj>number</obj>
        </schema>
      </schemas>
    </entry>
    <entry category="1_CelestialBody" id="1_CelestialBody_train_71">
      <text>1147 Stavropolis was discovered by Grigory Neujmin.</text>
      <triples>
        <triple>
          <sub>1147_Stavropolis</sub>
          <rel>discoverer</rel>
          <obj>Grigory_Neujmin</obj>
        </triple>
      </triples>
      <schemas>
        <schema>
          <sub>Asteroid</sub>
          <rel>discoverer</rel>
          <obj>Astronomer</obj>
        </schema>
      </schemas>
    </entry>
    <entry category="1_CelestialBody" id="1_CelestialBody_train_72">
      <text>10 Hygiea has a rotation period of 198803.</text>
      <triples>
        <triple>
          <sub>10_Hygiea</sub>
          <rel>rotationPeriod</rel>
          <obj>198803</obj>
        </triple>
      </triples>
      <schemas>
        <schema>
          <sub>Asteroid</sub>
          <rel>rotationPeriod</rel>
          <obj>number</obj>
        </schema>
      </schemas>
    </entry>
    <entry category="1_CelestialBody" id="1_CelestialBody_train_73">
      <text>The former name of 1000 Piazzia is "1923 NZ1951 OB".</text>
      <triples>
        <triple>
          <sub>1000_Piazzia</sub>
          <rel>formerName</rel>
          <obj>1923_NZ1951_OB</obj>
        </triple>
      </triples>
      <schemas>
        <schema>
          <sub>Asteroid</sub>
          <rel>formerName</rel>
          <obj>Asteroid</obj>
        </schema>
      </schemas>
    </entry>
    <entry category="1_CelestialBody" id="1_CelestialBody_train_74">
      <text>(29075) 1950 DA has an epoch date of August 27th 2011.</text>
      <triples>
        <triple>
          <sub>(29075)_1950_DA</sub>
          <rel>epoch</rel>
          <obj>2011-08-27</obj>
        </triple>
      </triples>
      <schemas>
        <schema>
          <sub>Asteroid</sub>
          <rel>epoch</rel>
          <obj>Date</obj>
        </schema>
      </schemas>
    </entry>
    <entry category="1_CelestialBody" id="1_CelestialBody_train_75">
      <text>(66063) 1998 RO1 has a periapsis measuring 41498400000.</text>
      <triples>
        <triple>
          <sub>(66063)_1998_RO1</sub>
          <rel>periapsis</rel>
          <obj>41498400000</obj>
        </triple>
      </triples>
      <schemas>
        <schema>
          <sub>Asteroid</sub>
          <rel>periapsis</rel>
          <obj>number</obj>
        </schema>
      </schemas>
    </entry>
    <entry category="1_CelestialBody" id="1_CelestialBody_train_76">
      <text>The epoch of 1000 Piazzia is 2015-06-27.</text>
      <triples>
        <triple>
          <sub>1000_Piazzia</sub>
          <rel>epoch</rel>
          <obj>2015-06-27</obj>
        </triple>
      </triples>
      <schemas>
        <schema>
          <sub>Asteroid</sub>
          <rel>epoch</rel>
          <obj>Date</obj>
        </schema>
      </schemas>
    </entry>
    <entry category="1_CelestialBody" id="1_CelestialBody_train_77">
      <text>1101 Clematis has an orbital period of 183309000.</text>
      <triples>
        <triple>
          <sub>1101_Clematis</sub>
          <rel>orbitalPeriod</rel>
          <obj>183309000</obj>
        </triple>
      </triples>
      <schemas>
        <schema>
          <sub>Asteroid</sub>
          <rel>orbitalPeriod</rel>
          <obj>number</obj>
        </schema>
      </schemas>
    </entry>
    <entry category="1_CelestialBody" id="1_CelestialBody_train_78">
      <text>1099 Figneria has an escape velocity of 0.0155 kilometres per second.</text>
      <triples>
        <triple>
          <sub>1099_Figneria</sub>
          <rel>escapeVelocity</rel>
          <obj>0.0155</obj>
        </triple>
      </triples>
      <schemas>
        <schema>
          <sub>Asteroid</sub>
          <rel>escapeVelocity</rel>
          <obj>number</obj>
        </schema>
      </schemas>
    </entry>
    <entry category="1_CelestialBody" id="1_CelestialBody_train_79">
      <text>10 Hygiea has a surface area of 837080.744 square kilometres.</text>
      <triples>
        <triple>
          <sub>10_Hygiea</sub>
          <rel>surfaceArea</rel>
          <obj>837080.744</obj>
        </triple>
      </triples>
      <schemas>
        <schema>
          <sub>Asteroid</sub>
          <rel>surfaceArea</rel>
          <obj>number</obj>
        </schema>
      </schemas>
    </entry>
    <entry category="1_CelestialBody" id="1_CelestialBody_train_80">
      <text>The orbital period of 109 Felicitas is 139705000.</text>
      <triples>
        <triple>
          <sub>109_Felicitas</sub>
          <rel>orbitalPeriod</rel>
          <obj>139705000</obj>
        </triple>
      </triples>
      <schemas>
        <schema>
          <sub>Asteroid</sub>
          <rel>orbitalPeriod</rel>
          <obj>number</obj>
        </schema>
      </schemas>
    </entry>
    <entry category="1_CelestialBody" id="1_CelestialBody_train_81">
      <text>The celestial body known as 1000 Piazzia was formerly known as 1967 ED.</text>
      <triples>
        <triple>
          <sub>1000_Piazzia</sub>
          <rel>formerName</rel>
          <obj>1967_ED</obj>
        </triple>
      </triples>
      <schemas>
        <schema>
          <sub>Asteroid</sub>
          <rel>formerName</rel>
          <obj>Asteroid</obj>
        </schema>
      </schemas>
    </entry>
    <entry category="1_CelestialBody" id="1_CelestialBody_train_82">
      <text>Annibale de Gasparis discovered 10 Hygiea.</text>
      <triples>
        <triple>
          <sub>10_Hygiea</sub>
          <rel>discoverer</rel>
          <obj>Annibale_de_Gasparis</obj>
        </triple>
      </triples>
      <schemas>
        <schema>
          <sub>Asteroid</sub>
          <rel>discoverer</rel>
          <obj>Astronomer</obj>
        </schema>
      </schemas>
    </entry>
    <entry category="1_CelestialBody" id="1_CelestialBody_train_83">
      <text>1099 Figneria has a temperature of 156 kelvins.</text>
      <triples>
        <triple>
          <sub>1099_Figneria</sub>
          <rel>temperature</rel>
          <obj>156</obj>
        </triple>
      </triples>
      <schemas>
        <schema>
          <sub>Asteroid</sub>
          <rel>temperature</rel>
          <obj>number</obj>
        </schema>
      </schemas>
    </entry>
    <entry category="1_CelestialBody" id="1_CelestialBody_train_84">
      <text>N. R. Pogson was English.</text>
      <triples>
        <triple>
          <sub>N._R._Pogson</sub>
          <rel>nationality</rel>
          <obj>England</obj>
        </triple>
      </triples>
      <schemas>
        <schema>
          <sub>Astronomer</sub>
          <rel>nationality</rel>
          <obj>Country</obj>
        </schema>
      </schemas>
    </entry>
    <entry category="1_CelestialBody" id="1_CelestialBody_train_85">
      <text>1099 Figneria has a periapsis measurement of 349206000000.</text>
      <triples>
        <triple>
          <sub>1099_Figneria</sub>
          <rel>periapsis</rel>
          <obj>349206000000</obj>
        </triple>
      </triples>
      <schemas>
        <schema>
          <sub>Asteroid</sub>
          <rel>periapsis</rel>
          <obj>number</obj>
        </schema>
      </schemas>
    </entry>
    <entry category="1_CelestialBody" id="1_CelestialBody_train_86">
      <text>10 Hygiea has an apoapsis of 523951582.33968 kilometres.</text>
      <triples>
        <triple>
          <sub>10_Hygiea</sub>
          <rel>apoapsis</rel>
          <obj>523951582.33968</obj>
        </triple>
      </triples>
      <schemas>
        <schema>
          <sub>Asteroid</sub>
          <rel>apoapsis</rel>
          <obj>number</obj>
        </schema>
      </schemas>
    </entry>
    <entry category="1_CelestialBody" id="1_CelestialBody_train_87">
      <text>(19255) 1994 VK8 has a temperature of 43 kelvins.</text>
      <triples>
        <triple>
          <sub>(19255)_1994_VK8</sub>
          <rel>temperature</rel>
          <obj>43</obj>
        </triple>
      </triples>
      <schemas>
        <schema>
          <sub>Asteroid</sub>
          <rel>temperature</rel>
          <obj>number</obj>
        </schema>
      </schemas>
    </entry>
    <entry category="1_CelestialBody" id="1_CelestialBody_train_88">
      <text>The absolute magnitude of 1147 Stavropolis is 11.5.</text>
      <triples>
        <triple>
          <sub>1147_Stavropolis</sub>
          <rel>absoluteMagnitude</rel>
          <obj>11.5</obj>
        </triple>
      </triples>
      <schemas>
        <schema>
          <sub>Asteroid</sub>
          <rel>absoluteMagnitude</rel>
          <obj>number</obj>
        </schema>
      </schemas>
    </entry>
    <entry category="1_CelestialBody" id="1_CelestialBody_train_89">
      <text>1097 Vicia has a temperature of 171 kelvins.</text>
      <triples>
        <triple>
          <sub>1097_Vicia</sub>
          <rel>temperature</rel>
          <obj>171</obj>
        </triple>
      </triples>
      <schemas>
        <schema>
          <sub>Asteroid</sub>
          <rel>temperature</rel>
          <obj>number</obj>
        </schema>
      </schemas>
    </entry>
    <entry category="1_CelestialBody" id="1_CelestialBody_train_90">
      <text>Alan Fitzsimmons was the discoverer of (15788) 1993 SB.</text>
      <triples>
        <triple>
          <sub>(15788)_1993_SB</sub>
          <rel>discoverer</rel>
          <obj>Alan_Fitzsimmons</obj>
        </triple>
      </triples>
      <schemas>
        <schema>
          <sub>Asteroid</sub>
          <rel>discoverer</rel>
          <obj>Astronomer</obj>
        </schema>
      </schemas>
    </entry>
    <entry category="1_CelestialBody" id="1_CelestialBody_train_91">
      <text>A911 MD is the former name of 1001 Gaussia.</text>
      <triples>
        <triple>
          <sub>1001_Gaussia</sub>
          <rel>formerName</rel>
          <obj>A911_MD</obj>
        </triple>
      </triples>
      <schemas>
        <schema>
          <sub>Asteroid</sub>
          <rel>formerName</rel>
          <obj>Asteroid</obj>
        </schema>
      </schemas>
    </entry>
    <entry category="1_CelestialBody" id="1_CelestialBody_train_92">
      <text>11264 Claudiomaccone has a periapsis of 296521000 (kilometres).</text>
      <triples>
        <triple>
          <sub>11264_Claudiomaccone</sub>
          <rel>periapsis</rel>
          <obj>296521000</obj>
        </triple>
      </triples>
      <schemas>
        <schema>
          <sub>Asteroid</sub>
          <rel>periapsis</rel>
          <obj>number</obj>
        </schema>
      </schemas>
    </entry>
    <entry category="1_CelestialBody" id="1_CelestialBody_train_93">
      <text>101 Helena has an escape velocity of 0.0348 km/s.</text>
      <triples>
        <triple>
          <sub>101_Helena</sub>
          <rel>escapeVelocity</rel>
          <obj>0.0348</obj>
        </triple>
      </triples>
      <schemas>
        <schema>
          <sub>Asteroid</sub>
          <rel>escapeVelocity</rel>
          <obj>number</obj>
        </schema>
      </schemas>
    </entry>
    <entry category="1_CelestialBody" id="1_CelestialBody_train_94">
      <text>(410777) 2009 FD has a minimum temperature of 211 kelvins.</text>
      <triples>
        <triple>
          <sub>(410777)_2009_FD</sub>
          <rel>minimumTemperature</rel>
          <obj>211</obj>
        </triple>
      </triples>
      <schemas>
        <schema>
          <sub>Asteroid</sub>
          <rel>minimumTemperature</rel>
          <obj>number</obj>
        </schema>
      </schemas>
    </entry>
    <entry category="1_CelestialBody" id="1_CelestialBody_train_95">
      <text>103 Hera has an apoapsis of 437170000 (kilometres).</text>
      <triples>
        <triple>
          <sub>103_Hera</sub>
          <rel>apoapsis</rel>
          <obj>437170000</obj>
        </triple>
      </triples>
      <schemas>
        <schema>
          <sub>Asteroid</sub>
          <rel>apoapsis</rel>
          <obj>number</obj>
        </schema>
      </schemas>
    </entry>
    <entry category="1_CelestialBody" id="1_CelestialBody_train_96">
      <text>(410777) 2009 FD has an apoapsis of 259776702.47055 kilometres.</text>
      <triples>
        <triple>
          <sub>(410777)_2009_FD</sub>
          <rel>apoapsis</rel>
          <obj>259776702.47055</obj>
        </triple>
      </triples>
      <schemas>
        <schema>
          <sub>Asteroid</sub>
          <rel>apoapsis</rel>
          <obj>number</obj>
        </schema>
      </schemas>
    </entry>
    <entry category="1_CelestialBody" id="1_CelestialBody_train_97">
      <text>The average speed of (19255) 1994 VK8 is 4.56 km per sec.</text>
      <triples>
        <triple>
          <sub>(19255)_1994_VK8</sub>
          <rel>averageSpeed</rel>
          <obj>4.56</obj>
        </triple>
      </triples>
      <schemas>
        <schema>
          <sub>Asteroid</sub>
          <rel>averageSpeed</rel>
          <obj>number</obj>
        </schema>
      </schemas>
    </entry>
    <entry category="1_CelestialBody" id="1_CelestialBody_train_98">
      <text>101 Helena has an absolute magnitude of 8.33.</text>
      <triples>
        <triple>
          <sub>101_Helena</sub>
          <rel>absoluteMagnitude</rel>
          <obj>8.33</obj>
        </triple>
      </triples>
      <schemas>
        <schema>
          <sub>Asteroid</sub>
          <rel>absoluteMagnitude</rel>
          <obj>number</obj>
        </schema>
      </schemas>
    </entry>
    <entry category="1_CelestialBody" id="1_CelestialBody_train_99">
      <text>(410777) 2009 FD has a mean temperature of 258 kelvins.</text>
      <triples>
        <triple>
          <sub>(410777)_2009_FD</sub>
          <rel>meanTemperature</rel>
          <obj>258</obj>
        </triple>
      </triples>
      <schemas>
        <schema>
          <sub>Asteroid</sub>
          <rel>meanTemperature</rel>
          <obj>number</obj>
        </schema>
      </schemas>
    </entry>
    <entry category="1_CelestialBody" id="1_CelestialBody_train_100">
      <text>110 Lydia has an escape velocity of 0.0455 kilometres per second.</text>
      <triples>
        <triple>
          <sub>110_Lydia</sub>
          <rel>escapeVelocity</rel>
          <obj>0.0455</obj>
        </triple>
      </triples>
      <schemas>
        <schema>
          <sub>Asteroid</sub>
          <rel>escapeVelocity</rel>
          <obj>number</obj>
        </schema>
      </schemas>
    </entry>
    <entry category="1_CelestialBody" id="1_CelestialBody_train_101">
      <text>11264 Claudiomaccone has an orbital period of 1513.722 days.</text>
      <triples>
        <triple>
          <sub>11264_Claudiomaccone</sub>
          <rel>orbitalPeriod</rel>
          <obj>1513.722</obj>
        </triple>
      </triples>
      <schemas>
        <schema>
          <sub>Asteroid</sub>
          <rel>orbitalPeriod</rel>
          <obj>number</obj>
        </schema>
      </schemas>
    </entry>
    <entry category="1_CelestialBody" id="1_CelestialBody_train_102">
      <text>11264 Claudiomaccone has the epoch date of 26 November 2005.</text>
      <triples>
        <triple>
          <sub>11264_Claudiomaccone</sub>
          <rel>epoch</rel>
          <obj>2005-11-26</obj>
        </triple>
      </triples>
      <schemas>
        <schema>
          <sub>Asteroid</sub>
          <rel>epoch</rel>
          <obj>Date</obj>
        </schema>
      </schemas>
    </entry>
    <entry category="1_CelestialBody" id="1_CelestialBody_train_103">
      <text>(410777) 2009 FD has an orbital period of 39447000.</text>
      <triples>
        <triple>
          <sub>(410777)_2009_FD</sub>
          <rel>orbitalPeriod</rel>
          <obj>39447000</obj>
        </triple>
      </triples>
      <schemas>
        <schema>
          <sub>Asteroid</sub>
          <rel>orbitalPeriod</rel>
          <obj>number</obj>
        </schema>
      </schemas>
    </entry>
    <entry category="1_CelestialBody" id="1_CelestialBody_train_104">
      <text>Grigory Neujmin's date of death was December 17, 1946.</text>
      <triples>
        <triple>
          <sub>Grigory_Neujmin</sub>
          <rel>deathDate</rel>
          <obj>1946-12-17</obj>
        </triple>
      </triples>
      <schemas>
        <schema>
          <sub>Astronomer</sub>
          <rel>deathDate</rel>
          <obj>Date</obj>
        </schema>
      </schemas>
    </entry>
    <entry category="1_CelestialBody" id="1_CelestialBody_train_105">
      <text>The escape velocity of 1101 Clematis is 0.02 km/sec.</text>
      <triples>
        <triple>
          <sub>1101_Clematis</sub>
          <rel>escapeVelocity</rel>
          <obj>0.02</obj>
        </triple>
      </triples>
      <schemas>
        <schema>
          <sub>Asteroid</sub>
          <rel>escapeVelocity</rel>
          <obj>number</obj>
        </schema>
      </schemas>
    </entry>
    <entry category="1_CelestialBody" id="1_CelestialBody_train_106">
      <text>103 Hera was discovered by James Craig Watson.</text>
      <triples>
        <triple>
          <sub>103_Hera</sub>
          <rel>discoverer</rel>
          <obj>James_Craig_Watson</obj>
        </triple>
      </triples>
      <schemas>
        <schema>
          <sub>Asteroid</sub>
          <rel>discoverer</rel>
          <obj>Astronomer</obj>
        </schema>
      </schemas>
    </entry>
    <entry category="1_CelestialBody" id="1_CelestialBody_train_107">
      <text>(19255) 1994 VK8 has an orbital period of 8788850000.</text>
      <triples>
        <triple>
          <sub>(19255)_1994_VK8</sub>
          <rel>orbitalPeriod</rel>
          <obj>8788850000</obj>
        </triple>
      </triples>
      <schemas>
        <schema>
          <sub>Asteroid</sub>
          <rel>orbitalPeriod</rel>
          <obj>number</obj>
        </schema>
      </schemas>
    </entry>
    <entry category="1_CelestialBody" id="1_CelestialBody_train_108">
      <text>1089 Tama has an apoapsis of 373513000 kilometres.</text>
      <triples>
        <triple>
          <sub>1089_Tama</sub>
          <rel>apoapsis</rel>
          <obj>373513000</obj>
        </triple>
      </triples>
      <schemas>
        <schema>
          <sub>Asteroid</sub>
          <rel>apoapsis</rel>
          <obj>number</obj>
        </schema>
      </schemas>
    </entry>
    <entry category="1_CelestialBody" id="1_CelestialBody_train_109">
      <text>(29075) 1950 DA has a rotation period of 7637.76.</text>
      <triples>
        <triple>
          <sub>(29075)_1950_DA</sub>
          <rel>rotationPeriod</rel>
          <obj>7637.76</obj>
        </triple>
      </triples>
      <schemas>
        <schema>
          <sub>Asteroid</sub>
          <rel>rotationPeriod</rel>
          <obj>number</obj>
        </schema>
      </schemas>
    </entry>
    <entry category="1_CelestialBody" id="1_CelestialBody_train_110">
      <text>101 Helena was discovered on August 15th 1868.</text>
      <triples>
        <triple>
          <sub>101_Helena</sub>
          <rel>discovered</rel>
          <obj>1868-08-15</obj>
        </triple>
      </triples>
      <schemas>
        <schema>
          <sub>Asteroid</sub>
          <rel>discovered</rel>
          <obj>Date</obj>
        </schema>
      </schemas>
    </entry>
    <entry category="1_CelestialBody" id="1_CelestialBody_train_111">
      <text>Grigory Neujmin was born on January 1, 1886.</text>
      <triples>
        <triple>
          <sub>Grigory_Neujmin</sub>
          <rel>birthDate</rel>
          <obj>1886-01-01</obj>
        </triple>
      </triples>
      <schemas>
        <schema>
          <sub>Astronomer</sub>
          <rel>birthDate</rel>
          <obj>Date</obj>
        </schema>
      </schemas>
    </entry>
    <entry category="1_CelestialBody" id="1_CelestialBody_train_112">
      <text>The periapsis of 1147 Stavropolis is 260855000000.</text>
      <triples>
        <triple>
          <sub>1147_Stavropolis</sub>
          <rel>periapsis</rel>
          <obj>260855000000</obj>
        </triple>
      </triples>
      <schemas>
        <schema>
          <sub>Asteroid</sub>
          <rel>periapsis</rel>
          <obj>number</obj>
        </schema>
      </schemas>
    </entry>
    <entry category="1_CelestialBody" id="1_CelestialBody_train_113">
      <text>110 Lydia travels at an average speed of 17.99 kilometres per second.</text>
      <triples>
        <triple>
          <sub>110_Lydia</sub>
          <rel>averageSpeed</rel>
          <obj>17.99</obj>
        </triple>
      </triples>
      <schemas>
        <schema>
          <sub>Asteroid</sub>
          <rel>averageSpeed</rel>
          <obj>number</obj>
        </schema>
      </schemas>
    </entry>
    <entry category="1_CelestialBody" id="1_CelestialBody_train_114">
      <text>103 Hera has a periapsis measurement of 371240000 (kilometres).</text>
      <triples>
        <triple>
          <sub>103_Hera</sub>
          <rel>periapsis</rel>
          <obj>371240000</obj>
        </triple>
      </triples>
      <schemas>
        <schema>
          <sub>Asteroid</sub>
          <rel>periapsis</rel>
          <obj>number</obj>
        </schema>
      </schemas>
    </entry>
    <entry category="1_CelestialBody" id="1_CelestialBody_train_115">
      <text>The former name of 10 Hygiea was A900 GA.</text>
      <triples>
        <triple>
          <sub>10_Hygiea</sub>
          <rel>formerName</rel>
          <obj>A900_GA</obj>
        </triple>
      </triples>
      <schemas>
        <schema>
          <sub>Asteroid</sub>
          <rel>formerName</rel>
          <obj>Asteroid</obj>
        </schema>
      </schemas>
    </entry>
    <entry category="1_CelestialBody" id="1_CelestialBody_train_116">
      <text>Sergey Belyavsky discovered 1001 Gaussia.</text>
      <triples>
        <triple>
          <sub>1001_Gaussia</sub>
          <rel>discoverer</rel>
          <obj>Sergey_Belyavsky</obj>
        </triple>
      </triples>
      <schemas>
        <schema>
          <sub>Asteroid</sub>
          <rel>discoverer</rel>
          <obj>Astronomer</obj>
        </schema>
      </schemas>
    </entry>
    <entry category="1_CelestialBody" id="1_CelestialBody_train_117">
      <text>The average speed of 1099 Figneria is 16.37 km per sec.</text>
      <triples>
        <triple>
          <sub>1099_Figneria</sub>
          <rel>averageSpeed</rel>
          <obj>16.37</obj>
        </triple>
      </triples>
      <schemas>
        <schema>
          <sub>Asteroid</sub>
          <rel>averageSpeed</rel>
          <obj>number</obj>
        </schema>
      </schemas>
    </entry>
    <entry category="1_CelestialBody" id="1_CelestialBody_train_118">
      <text>1001 Gaussia's epoch date is 2015-06-27.</text>
      <triples>
        <triple>
          <sub>1001_Gaussia</sub>
          <rel>epoch</rel>
          <obj>2015-06-27</obj>
        </triple>
      </triples>
      <schemas>
        <schema>
          <sub>Asteroid</sub>
          <rel>epoch</rel>
          <obj>Date</obj>
        </schema>
      </schemas>
    </entry>
    <entry category="1_CelestialBody" id="1_CelestialBody_train_119">
      <text>1101 Clematis has a mass of 5.7 kgs.</text>
      <triples>
        <triple>
          <sub>1101_Clematis</sub>
          <rel>mass</rel>
          <obj>5.7</obj>
        </triple>
      </triples>
      <schemas>
        <schema>
          <sub>Asteroid</sub>
          <rel>mass</rel>
          <obj>number</obj>
        </schema>
      </schemas>
    </entry>
    <entry category="1_CelestialBody" id="1_CelestialBody_train_120">
      <text>(29075) 1950 DA has a density of 3.5 kilograms.</text>
      <triples>
        <triple>
          <sub>(29075)_1950_DA</sub>
          <rel>density</rel>
          <obj>3.5</obj>
        </triple>
      </triples>
      <schemas>
        <schema>
          <sub>Asteroid</sub>
          <rel>density</rel>
          <obj>number</obj>
        </schema>
      </schemas>
    </entry>
    <entry category="1_CelestialBody" id="1_CelestialBody_train_121">
      <text>110 Lydia has an epoch date of December 31st 2006.</text>
      <triples>
        <triple>
          <sub>110_Lydia</sub>
          <rel>epoch</rel>
          <obj>2006-12-31</obj>
        </triple>
      </triples>
      <schemas>
        <schema>
          <sub>Asteroid</sub>
          <rel>epoch</rel>
          <obj>Date</obj>
        </schema>
      </schemas>
    </entry>
    <entry category="1_CelestialBody" id="1_CelestialBody_train_122">
      <text>The epoch date of 109 Felicitas is 31 December 2006.</text>
      <triples>
        <triple>
          <sub>109_Felicitas</sub>
          <rel>epoch</rel>
          <obj>2006-12-31</obj>
        </triple>
      </triples>
      <schemas>
        <schema>
          <sub>Asteroid</sub>
          <rel>epoch</rel>
          <obj>Date</obj>
        </schema>
      </schemas>
    </entry>
    <entry category="1_CelestialBody" id="1_CelestialBody_train_123">
      <text>The apoapsis for (15788) 1993 SB is 7715100000 (kilometres).</text>
      <triples>
        <triple>
          <sub>(15788)_1993_SB</sub>
          <rel>apoapsis</rel>
          <obj>7715100000</obj>
        </triple>
      </triples>
      <schemas>
        <schema>
          <sub>Asteroid</sub>
          <rel>apoapsis</rel>
          <obj>number</obj>
        </schema>
      </schemas>
    </entry>
    <entry category="1_CelestialBody" id="1_CelestialBody_train_124">
      <text>11264 Claudiomaccone has an average speed of 18.29 kilometres per second.</text>
      <triples>
        <triple>
          <sub>11264_Claudiomaccone</sub>
          <rel>averageSpeed</rel>
          <obj>18.29</obj>
        </triple>
      </triples>
      <schemas>
        <schema>
          <sub>Asteroid</sub>
          <rel>averageSpeed</rel>
          <obj>number</obj>
        </schema>
      </schemas>
    </entry>
    <entry category="1_CelestialBody" id="1_CelestialBody_train_125">
      <text>103 Hera has a rotation period of 85466.9.</text>
      <triples>
        <triple>
          <sub>103_Hera</sub>
          <rel>rotationPeriod</rel>
          <obj>85466.9</obj>
        </triple>
      </triples>
      <schemas>
        <schema>
          <sub>Asteroid</sub>
          <rel>rotationPeriod</rel>
          <obj>number</obj>
        </schema>
      </schemas>
    </entry>
    <entry category="1_CelestialBody" id="1_CelestialBody_train_126">
      <text>10 Hygiea has an epoch date of June 27th 2015.</text>
      <triples>
        <triple>
          <sub>10_Hygiea</sub>
          <rel>epoch</rel>
          <obj>2015-06-27</obj>
        </triple>
      </triples>
      <schemas>
        <schema>
          <sub>Asteroid</sub>
          <rel>epoch</rel>
          <obj>Date</obj>
        </schema>
      </schemas>
    </entry>
    <entry category="1_CelestialBody" id="1_CelestialBody_train_127">
      <text>109 Felicitas has an average speed of 17.73 kilometres per second.</text>
      <triples>
        <triple>
          <sub>109_Felicitas</sub>
          <rel>averageSpeed</rel>
          <obj>17.73</obj>
        </triple>
      </triples>
      <schemas>
        <schema>
          <sub>Asteroid</sub>
          <rel>averageSpeed</rel>
          <obj>number</obj>
        </schema>
      </schemas>
    </entry>
    <entry category="1_CelestialBody" id="1_CelestialBody_train_128">
      <text>1089 Tama has an escape velocity of 0.0068 kilometres per second.</text>
      <triples>
        <triple>
          <sub>1089_Tama</sub>
          <rel>escapeVelocity</rel>
          <obj>0.0068</obj>
        </triple>
      </triples>
      <schemas>
        <schema>
          <sub>Asteroid</sub>
          <rel>escapeVelocity</rel>
          <obj>number</obj>
        </schema>
      </schemas>
    </entry>
    <entry category="1_CelestialBody" id="1_CelestialBody_train_129">
      <text>1101 Clematis has an apoapsis of 520906000 kilometres.</text>
      <triples>
        <triple>
          <sub>1101_Clematis</sub>
          <rel>apoapsis</rel>
          <obj>520906000</obj>
        </triple>
      </triples>
      <schemas>
        <schema>
          <sub>Asteroid</sub>
          <rel>apoapsis</rel>
          <obj>number</obj>
        </schema>
      </schemas>
    </entry>
    <entry category="1_CelestialBody" id="1_CelestialBody_train_130">
      <text>1097 Vicia was formerly known as "1928 PC".</text>
      <triples>
        <triple>
          <sub>1097_Vicia</sub>
          <rel>formerName</rel>
          <obj>1928_PC</obj>
        </triple>
      </triples>
      <schemas>
        <schema>
          <sub>Asteroid</sub>
          <rel>formerName</rel>
          <obj>Asteroid</obj>
        </schema>
      </schemas>
    </entry>
    <entry category="1_CelestialBody" id="1_CelestialBody_train_131">
      <text>(29075) 1950 DA has an orbital period of 69862200.</text>
      <triples>
        <triple>
          <sub>(29075)_1950_DA</sub>
          <rel>orbitalPeriod</rel>
          <obj>69862200</obj>
        </triple>
      </triples>
      <schemas>
        <schema>
          <sub>Asteroid</sub>
          <rel>orbitalPeriod</rel>
          <obj>number</obj>
        </schema>
      </schemas>
    </entry>
    <entry category="1_CelestialBody" id="1_CelestialBody_train_132">
      <text>109 Felicitas has an apoapsis of 523329000 kilometres.</text>
      <triples>
        <triple>
          <sub>109_Felicitas</sub>
          <rel>apoapsis</rel>
          <obj>523329000</obj>
        </triple>
      </triples>
      <schemas>
        <schema>
          <sub>Asteroid</sub>
          <rel>apoapsis</rel>
          <obj>number</obj>
        </schema>
      </schemas>
    </entry>
    <entry category="1_CelestialBody" id="1_CelestialBody_train_133">
      <text>1089 Tama has an average speed of 19.94 kilometres per second.</text>
      <triples>
        <triple>
          <sub>1089_Tama</sub>
          <rel>averageSpeed</rel>
          <obj>19.94</obj>
        </triple>
      </triples>
      <schemas>
        <schema>
          <sub>Asteroid</sub>
          <rel>averageSpeed</rel>
          <obj>number</obj>
        </schema>
      </schemas>
    </entry>
    <entry category="1_CelestialBody" id="1_CelestialBody_train_134">
      <text>1097 Vicia has a periapsis of 279142000000.</text>
      <triples>
        <triple>
          <sub>1097_Vicia</sub>
          <rel>periapsis</rel>
          <obj>279142000000</obj>
        </triple>
      </triples>
      <schemas>
        <schema>
          <sub>Asteroid</sub>
          <rel>periapsis</rel>
          <obj>number</obj>
        </schema>
      </schemas>
    </entry>
    <entry category="1_CelestialBody" id="1_CelestialBody_train_135">
      <text>The temperature of 101 Helena is 173 kelvins.</text>
      <triples>
        <triple>
          <sub>101_Helena</sub>
          <rel>temperature</rel>
          <obj>173</obj>
        </triple>
      </triples>
      <schemas>
        <schema>
          <sub>Asteroid</sub>
          <rel>temperature</rel>
          <obj>number</obj>
        </schema>
      </schemas>
    </entry>
    <entry category="1_CelestialBody" id="1_CelestialBody_train_136">
      <text>The apoapsis for 11264 Claudiomaccone is 475426000 (kilometres).</text>
      <triples>
        <triple>
          <sub>11264_Claudiomaccone</sub>
          <rel>apoapsis</rel>
          <obj>475426000</obj>
        </triple>
      </triples>
      <schemas>
        <schema>
          <sub>Asteroid</sub>
          <rel>apoapsis</rel>
          <obj>number</obj>
        </schema>
      </schemas>
    </entry>
    <entry category="1_CelestialBody" id="1_CelestialBody_train_137">
      <text>(66063) 1998 RO1 has a minimum temperature of -71 degrees Celsius.</text>
      <triples>
        <triple>
          <sub>(66063)_1998_RO1</sub>
          <rel>minimumTemperature</rel>
          <obj>-71</obj>
        </triple>
      </triples>
      <schemas>
        <schema>
          <sub>Asteroid</sub>
          <rel>minimumTemperature</rel>
          <obj>number</obj>
        </schema>
      </schemas>
    </entry>
  </entries>
</benchmark>
